{
    "information": {
        "filename": "08.jpg",
        "resolution": [
            1920,
            1080
        ]
    },
    "Scene_meta": {
        "zone": "세종-청사/시청 구간 (6-STOP)",
        "edge_case": [
            "대항차 전방 cutin 예측",
            "선행차 주행",
            "편향주행",
            "곡선 구간 차선 유지",
            "횡단보도",
            "비보호 우회전",
            "신호등 정지신호"
        ],
        "scene_number": "08_150401_220615"
    },
    "Environment_meta": {
        "weather": "흐림",
        "date": "2022-06-15",
        "time": "15:04:01",
        "car_type": "G80",
        "traffic_Type": 0,
        "speed_type": 1,
        "road_type": "도심 3차로 이상"
    },
    "annotations": [
        {
            "polygon": [
                0,
                0,
                1920,
                0,
                1920,
                1080,
                0,
                1080
            ],
            "class": "background"
        },
        {
            "polygon": [
                797,
                788,
                797,
                785,
                798,
                784,
                805,
                784,
                806,
                785,
                806,
                789
            ],
            "class": "truck"
        },
        {
            "polygon": [
                0,
                834,
                181,
                829,
                306,
                828,
                546,
                804,
                602,
                797,
                639,
                792,
                644,
                795,
                687,
                790,
                709,
                787,
                771,
                786,
                828,
                786,
                855,
                804,
                1025,
                828,
                1032,
                843,
                1191,
                840,
                1502,
                806,
                1846,
                788,
                1849,
                972,
                1837,
                1080,
                0,
                1080
            ],
            "class": "freespace"
        },
        {
            "polygon": [
                1578,
                815,
                1646,
                831,
                1823,
                808,
                1823,
                797
            ],
            "class": "crossWalk"
        },
        {
            "polygon": [
                290,
                835,
                366,
                832,
                437,
                831,
                520,
                828,
                617,
                828,
                618,
                826,
                519,
                826,
                438,
                828,
                367,
                830,
                299,
                833
            ],
            "class": "stopLane"
        },
        {
            "polygon": [
                1830,
                910,
                1792,
                920,
                1729,
                949,
                1716,
                958,
                1700,
                972,
                1680,
                996,
                1669,
                1030,
                1663,
                1061,
                1663,
                1080,
                1920,
                1080,
                1920,
                972
            ],
            "class": "sideWalk"
        },
        {
            "polygon": [
                603,
                796,
                629,
                793,
                629,
                795,
                603,
                798
            ],
            "class": "curb"
        },
        {
            "polygon": [
                0,
                835,
                56,
                836,
                87,
                841,
                136,
                842,
                181,
                840,
                201,
                839,
                263,
                835,
                286,
                833,
                305,
                830,
                323,
                826,
                223,
                826,
                224,
                824,
                229,
                823,
                247,
                823,
                244,
                819,
                243,
                814,
                166,
                817,
                62,
                823,
                0,
                822
            ],
            "class": "sideWalk"
        },
        {
            "polygon": [
                0,
                832,
                63,
                833,
                87,
                841,
                0,
                840
            ],
            "class": "curb"
        },
        {
            "polygon": [
                0,
                826,
                13,
                826,
                13,
                830,
                17,
                830,
                17,
                829,
                26,
                829,
                26,
                818,
                0,
                817
            ],
            "class": "background"
        },
        {
            "polygon": [
                144,
                817,
                145,
                805,
                150,
                805,
                152,
                817
            ],
            "class": "rubberCone"
        },
        {
            "polygon": [
                131,
                812,
                28,
                815,
                31,
                824,
                30,
                826,
                30,
                830,
                36,
                830,
                48,
                830,
                56,
                830,
                68,
                832,
                79,
                835,
                89,
                839,
                96,
                840,
                126,
                840,
                136,
                840,
                190,
                838,
                195,
                836,
                196,
                834,
                195,
                832,
                191,
                832,
                184,
                829,
                179,
                825,
                174,
                821,
                164,
                814
            ],
            "class": "background"
        },
        {
            "polygon": [
                233,
                780,
                232,
                782,
                232,
                785,
                235,
                798,
                233,
                801,
                233,
                803,
                235,
                806,
                235,
                811,
                234,
                817,
                230,
                817,
                228,
                814,
                224,
                814,
                223,
                816,
                223,
                822,
                225,
                824,
                228,
                824,
                230,
                821,
                237,
                820,
                238,
                823,
                240,
                824,
                242,
                824,
                244,
                822,
                244,
                815,
                242,
                813,
                240,
                812,
                237,
                786,
                239,
                788,
                241,
                788,
                241,
                784,
                240,
                782,
                235,
                779
            ],
            "class": "twoWheeler"
        },
        {
            "polygon": [
                208,
                826,
                206,
                831,
                220,
                831,
                218,
                826,
                214,
                800,
                211,
                800
            ],
            "class": "rubberCone"
        },
        {
            "polygon": [
                535,
                804,
                295,
                827,
                286,
                833,
                536,
                808
            ],
            "class": "curb"
        },
        {
            "polygon": [
                252,
                833,
                262,
                833,
                256,
                809,
                253,
                809
            ],
            "class": "rubberCone"
        },
        {
            "polygon": [
                201,
                839,
                223,
                832,
                241,
                831,
                260,
                836
            ],
            "class": "curb"
        },
        {
            "polygon": [
                233,
                830,
                233,
                838,
                262,
                836,
                251,
                829
            ],
            "class": "background"
        },
        {
            "polygon": [
                1043,
                814,
                1077,
                814,
                1119,
                812,
                1329,
                806,
                1420,
                804,
                1603,
                788,
                1671,
                793,
                1844,
                778,
                1846,
                795,
                1667,
                819,
                1638,
                821,
                1512,
                821,
                1421,
                829,
                1303,
                836,
                1180,
                842,
                952,
                845,
                941,
                843,
                953,
                828
            ],
            "class": "sideWalk"
        },
        {
            "polygon": [
                1832,
                802,
                1839,
                792,
                1752,
                802,
                1667,
                819,
                1753,
                811
            ],
            "class": "curb"
        },
        {
            "polygon": [
                959,
                838,
                1175,
                837,
                1170,
                847,
                952,
                845
            ],
            "class": "curb"
        },
        {
            "polygon": [
                1831,
                814,
                1649,
                834,
                1670,
                834,
                1833,
                817
            ],
            "class": "crossWalk"
        },
        {
            "polygon": [
                1843,
                809,
                1785,
                815,
                1797,
                816,
                1843,
                811
            ],
            "class": "crossWalk"
        },
        {
            "polygon": [
                1839,
                835,
                1831,
                832,
                1783,
                838,
                1801,
                839
            ],
            "class": "crossWalk"
        },
        {
            "polygon": [
                1674,
                796,
                1689,
                796,
                1684,
                758,
                1679,
                758
            ],
            "class": "rubberCone"
        },
        {
            "polygon": [
                1712,
                801,
                1730,
                802,
                1735,
                797,
                1731,
                796,
                1726,
                759,
                1721,
                759,
                1717,
                797
            ],
            "class": "rubberCone"
        },
        {
            "polygon": [
                1548,
                802,
                1537,
                809,
                1531,
                813,
                1528,
                817,
                1524,
                822,
                1515,
                825,
                1513,
                827,
                1518,
                828,
                1529,
                827,
                1552,
                826,
                1586,
                825,
                1611,
                822,
                1638,
                819,
                1669,
                814,
                1697,
                808,
                1703,
                807,
                1709,
                806,
                1703,
                803,
                1697,
                801,
                1689,
                799,
                1683,
                798,
                1677,
                794,
                1670,
                789,
                1660,
                782
            ],
            "class": "background"
        },
        {
            "polygon": [
                1102,
                831,
                1117,
                831,
                1118,
                827,
                1127,
                828,
                1127,
                832,
                1131,
                832,
                1131,
                828,
                1146,
                828,
                1146,
                832,
                1177,
                830,
                1177,
                793,
                1107,
                797
            ],
            "class": "background"
        },
        {
            "polygon": [
                1675,
                762,
                1688,
                763,
                1688,
                770,
                1674,
                768
            ],
            "class": "background"
        },
        {
            "polygon": [
                738,
                589,
                797,
                587,
                797,
                601,
                738,
                604
            ],
            "class": "trafficLight"
        },
        {
            "polygon": [
                802,
                589,
                802,
                583,
                804,
                577,
                809,
                572,
                816,
                569,
                825,
                569,
                832,
                572,
                836,
                578,
                837,
                584,
                837,
                592,
                835,
                598,
                830,
                602,
                825,
                604,
                816,
                604,
                809,
                602,
                804,
                597
            ],
            "class": "trafficSign"
        },
        {
            "polygon": [
                732,
                717,
                751,
                717,
                751,
                722,
                732,
                722
            ],
            "class": "trafficLight"
        },
        {
            "polygon": [
                786,
                715,
                806,
                715,
                806,
                720,
                786,
                720
            ],
            "class": "trafficLight"
        },
        {
            "polygon": [
                731,
                722,
                736,
                721,
                740,
                722,
                744,
                720,
                749,
                720,
                758,
                721,
                758,
                726,
                730,
                727
            ],
            "class": "background"
        },
        {
            "polygon": [
                425,
                828,
                423,
                821,
                422,
                811,
                423,
                799,
                428,
                792,
                425,
                791,
                425,
                787,
                427,
                785,
                434,
                785,
                441,
                776,
                445,
                772,
                454,
                771,
                484,
                771,
                489,
                773,
                496,
                781,
                502,
                787,
                505,
                795,
                506,
                805,
                505,
                822,
                503,
                824,
                496,
                824,
                495,
                823,
                494,
                818,
                491,
                818,
                491,
                824,
                489,
                827,
                482,
                827,
                480,
                825,
                479,
                820,
                456,
                820,
                454,
                823,
                450,
                827,
                446,
                827,
                443,
                825,
                441,
                820,
                438,
                820,
                437,
                828,
                435,
                829,
                428,
                829
            ],
            "class": "vehicle"
        },
        {
            "polygon": [
                537,
                780,
                546,
                767,
                551,
                764,
                560,
                762,
                590,
                762,
                593,
                764,
                600,
                777,
                603,
                780,
                606,
                784,
                607,
                793,
                607,
                821,
                606,
                823,
                600,
                823,
                597,
                826,
                588,
                826,
                587,
                825,
                587,
                819,
                554,
                820,
                553,
                824,
                551,
                825,
                546,
                825,
                544,
                824,
                544,
                819,
                542,
                819,
                541,
                826,
                540,
                827,
                533,
                827,
                531,
                826,
                530,
                821,
                529,
                801,
                530,
                794,
                533,
                790,
                534,
                787,
                530,
                787,
                528,
                785,
                528,
                781,
                530,
                780
            ],
            "class": "vehicle"
        },
        {
            "polygon": [
                649,
                831,
                655,
                831,
                655,
                828,
                649,
                828
            ],
            "class": "bicycle"
        },
        {
            "polygon": [
                590,
                838,
                598,
                834,
                624,
                834,
                616,
                838
            ],
            "class": "crossWalk"
        },
        {
            "polygon": [
                583,
                834,
                594,
                830,
                615,
                830,
                602,
                833
            ],
            "class": "crossWalk"
        },
        {
            "polygon": [
                536,
                837,
                547,
                833,
                570,
                833,
                562,
                837
            ],
            "class": "crossWalk"
        },
        {
            "polygon": [
                534,
                833,
                542,
                830,
                567,
                830,
                557,
                833
            ],
            "class": "crossWalk"
        },
        {
            "polygon": [
                233,
                839,
                252,
                837,
                270,
                837,
                251,
                839
            ],
            "class": "crossWalk"
        },
        {
            "polygon": [
                321,
                839,
                342,
                837,
                361,
                837,
                344,
                839
            ],
            "class": "crossWalk"
        },
        {
            "polygon": [
                375,
                839,
                395,
                836,
                412,
                836,
                394,
                839
            ],
            "class": "crossWalk"
        },
        {
            "polygon": [
                424,
                838,
                443,
                834,
                460,
                834,
                446,
                837
            ],
            "class": "crossWalk"
        },
        {
            "polygon": [
                478,
                837,
                494,
                834,
                511,
                834,
                497,
                837
            ],
            "class": "crossWalk"
        },
        {
            "polygon": [
                484,
                834,
                498,
                831,
                515,
                831,
                499,
                834
            ],
            "class": "crossWalk"
        },
        {
            "polygon": [
                433,
                834,
                448,
                832,
                464,
                832,
                448,
                834
            ],
            "class": "crossWalk"
        },
        {
            "polygon": [
                380,
                836,
                398,
                833,
                413,
                833,
                397,
                836
            ],
            "class": "crossWalk"
        },
        {
            "polygon": [
                332,
                836,
                348,
                834,
                366,
                834,
                348,
                836
            ],
            "class": "crossWalk"
        },
        {
            "polygon": [
                555,
                841,
                574,
                844,
                575,
                842,
                566,
                841
            ],
            "class": "whiteLane"
        },
        {
            "polygon": [
                634,
                847,
                661,
                849,
                661,
                851,
                634,
                849
            ],
            "class": "whiteLane"
        },
        {
            "polygon": [
                276,
                848,
                323,
                846,
                324,
                849,
                277,
                851
            ],
            "class": "whiteLane"
        },
        {
            "polygon": [
                118,
                942,
                278,
                940,
                279,
                943,
                118,
                945
            ],
            "class": "whiteLane"
        },
        {
            "polygon": [
                408,
                934,
                573,
                927,
                574,
                931,
                409,
                937
            ],
            "class": "whiteLane"
        },
        {
            "polygon": [
                696,
                920,
                822,
                913,
                822,
                916,
                697,
                923
            ],
            "class": "whiteLane"
        },
        {
            "polygon": [
                1146,
                860,
                1215,
                859,
                1215,
                862,
                1146,
                863
            ],
            "class": "whiteLane"
        },
        {
            "polygon": [
                767,
                1043,
                866,
                1042,
                869,
                1080,
                752,
                1080
            ],
            "class": "crossWalk"
        },
        {
            "polygon": [
                481,
                1069,
                584,
                1070,
                574,
                1080,
                467,
                1080
            ],
            "class": "crossWalk"
        },
        {
            "polygon": [
                272,
                1036,
                361,
                1040,
                291,
                1080,
                181,
                1080
            ],
            "class": "crossWalk"
        },
        {
            "polygon": [
                61,
                1019,
                137,
                1025,
                0,
                1074,
                0,
                1039
            ],
            "class": "crossWalk"
        },
        {
            "polygon": [
                1719,
                1033,
                1809,
                1020,
                1809,
                1015,
                1796,
                996,
                1790,
                996,
                1779,
                944,
                1800,
                943,
                1807,
                941,
                1831,
                931,
                1828,
                920,
                1809,
                906,
                1811,
                890,
                1809,
                886,
                1804,
                883,
                1767,
                880,
                1758,
                846,
                1756,
                843,
                1749,
                844,
                1746,
                848,
                1731,
                1003,
                1713,
                1007
            ],
            "class": "rubberCone"
        },
        {
            "polygon": [
                1769,
                809,
                1790,
                809,
                1819,
                804,
                1813,
                794,
                1777,
                798
            ],
            "class": "background"
        },
        {
            "polygon": [
                1759,
                811,
                1775,
                810,
                1768,
                768,
                1763,
                768
            ],
            "class": "rubberCone"
        },
        {
            "polygon": [
                1691,
                835,
                1840,
                818,
                1841,
                821,
                1714,
                835
            ],
            "class": "crossWalk"
        },
        {
            "polygon": [
                1735,
                837,
                1834,
                825,
                1834,
                829,
                1756,
                837
            ],
            "class": "crossWalk"
        },
        {
            "polygon": [
                1799,
                948,
                1805,
                948,
                1806,
                760,
                1803,
                760
            ],
            "class": "background"
        },
        {
            "polygon": [
                1816,
                761,
                1818,
                775,
                1817,
                787,
                1816,
                796,
                1818,
                803,
                1822,
                820,
                1822,
                846,
                1823,
                894,
                1822,
                913,
                1820,
                956,
                1817,
                964,
                1818,
                988,
                1822,
                992,
                1836,
                992,
                1920,
                991,
                1920,
                759
            ],
            "class": "background"
        },
        {
            "polygon": [
                1145,
                1073,
                1261,
                1052,
                1265,
                1058,
                1365,
                1052,
                1368,
                1057,
                1274,
                1063,
                1279,
                1069
            ],
            "class": "roadMark"
        },
        {
            "polygon": [
                288,
                837,
                307,
                835,
                325,
                835,
                306,
                837
            ],
            "class": "crossWalk"
        },
        {
            "polygon": [
                281,
                839,
                300,
                837,
                318,
                837,
                299,
                839
            ],
            "class": "crossWalk"
        },
        {
            "polygon": [
                589,
                845,
                610,
                848,
                611,
                846,
                590,
                843
            ],
            "class": "whiteLane"
        },
        {
            "polygon": [
                0,
                945,
                3,
                945,
                3,
                948,
                0,
                948
            ],
            "class": "whiteLane"
        },
        {
            "polygon": [
                362,
                844,
                400,
                843,
                401,
                845,
                364,
                846
            ],
            "class": "whiteLane"
        },
        {
            "polygon": [
                687,
                850,
                722,
                854,
                721,
                857,
                686,
                853
            ],
            "class": "whiteLane"
        },
        {
            "polygon": [
                767,
                858,
                812,
                858,
                813,
                860,
                767,
                860
            ],
            "class": "whiteLane"
        },
        {
            "polygon": [
                836,
                857,
                872,
                860,
                870,
                862,
                834,
                859
            ],
            "class": "whiteLane"
        },
        {
            "polygon": [
                925,
                861,
                977,
                862,
                976,
                865,
                924,
                864
            ],
            "class": "whiteLane"
        },
        {
            "polygon": [
                1023,
                862,
                1087,
                861,
                1087,
                864,
                1023,
                865
            ],
            "class": "whiteLane"
        },
        {
            "polygon": [
                955,
                904,
                1086,
                897,
                1086,
                901,
                956,
                908
            ],
            "class": "whiteLane"
        },
        {
            "polygon": [
                692,
                798,
                695,
                798,
                695,
                784,
                692,
                784
            ],
            "class": "background"
        },
        {
            "polygon": [
                714,
                805,
                634,
                828,
                628,
                826,
                705,
                805
            ],
            "class": "yellowLane"
        },
        {
            "polygon": [
                632,
                826,
                684,
                812,
                684,
                799,
                691,
                798,
                691,
                785,
                654,
                786,
                654,
                792,
                632,
                793
            ],
            "class": "fense"
        },
        {
            "polygon": [
                627,
                827,
                631,
                827,
                631,
                795,
                627,
                795
            ],
            "class": "background"
        },
        {
            "polygon": [
                660,
                834,
                649,
                838,
                667,
                838
            ],
            "class": "crossWalk"
        },
        {
            "polygon": [
                645,
                833,
                661,
                833,
                662,
                830,
                647,
                830
            ],
            "class": "crossWalk"
        },
        {
            "polygon": [
                643,
                822,
                651,
                829,
                655,
                830,
                656,
                829,
                656,
                826,
                653,
                823,
                653,
                821,
                657,
                813,
                657,
                810,
                656,
                807,
                652,
                804,
                649,
                810
            ],
            "class": "rider"
        },
        {
            "polygon": [
                628,
                796,
                628,
                805,
                632,
                808,
                632,
                812,
                613,
                811,
                611,
                813,
                611,
                816,
                617,
                817,
                615,
                819,
                612,
                822,
                610,
                827,
                611,
                833,
                613,
                839,
                619,
                842,
                623,
                842,
                629,
                842,
                633,
                839,
                636,
                836,
                638,
                831,
                639,
                834,
                642,
                835,
                646,
                835,
                648,
                834,
                649,
                832,
                649,
                827,
                654,
                823,
                662,
                816,
                663,
                819,
                660,
                824,
                659,
                828,
                659,
                832,
                661,
                837,
                665,
                841,
                671,
                842,
                678,
                842,
                683,
                840,
                685,
                837,
                687,
                832,
                687,
                828,
                685,
                822,
                681,
                819,
                678,
                816,
                673,
                813,
                673,
                801,
                672,
                799,
                664,
                799,
                664,
                795,
                665,
                791,
                662,
                789,
                658,
                795,
                651,
                795,
                651,
                797,
                654,
                799,
                658,
                802,
                659,
                806,
                660,
                813,
                637,
                813,
                637,
                806
            ],
            "class": "bicycle"
        },
        {
            "polygon": [
                634,
                822,
                639,
                829,
                642,
                830,
                644,
                828,
                644,
                826,
                642,
                823,
                642,
                820,
                652,
                813,
                656,
                810,
                655,
                805,
                653,
                802,
                647,
                800,
                642,
                798,
                640,
                796,
                640,
                794,
                647,
                793,
                650,
                791,
                655,
                795,
                658,
                795,
                659,
                794,
                659,
                793,
                656,
                792,
                651,
                787,
                647,
                782,
                641,
                775,
                637,
                772,
                640,
                771,
                643,
                768,
                643,
                765,
                643,
                759,
                640,
                757,
                635,
                757,
                632,
                758,
                631,
                762,
                632,
                767,
                627,
                769,
                624,
                773,
                623,
                776,
                623,
                784,
                626,
                795,
                628,
                801,
                631,
                805,
                637,
                808,
                643,
                809,
                643,
                811,
                634,
                819
            ],
            "class": "rider"
        },
        {
            "polygon": [
                709,
                789,
                708,
                785,
                708,
                770,
                709,
                769,
                721,
                769,
                724,
                772,
                724,
                788,
                723,
                789,
                719,
                789,
                718,
                788,
                712,
                788,
                712,
                789
            ],
            "class": "truck"
        },
        {
            "polygon": [
                725,
                789,
                725,
                780,
                726,
                777,
                728,
                776,
                738,
                776,
                740,
                778,
                741,
                781,
                741,
                788,
                729,
                788,
                729,
                789
            ],
            "class": "vehicle"
        },
        {
            "polygon": [
                766,
                781,
                767,
                778,
                769,
                776,
                779,
                776,
                781,
                778,
                782,
                781,
                782,
                786,
                779,
                786,
                778,
                785,
                767,
                785
            ],
            "class": "vehicle"
        },
        {
            "polygon": [
                730,
                791,
                726,
                790,
                728,
                788,
                733,
                786,
                737,
                784,
                740,
                781,
                742,
                778,
                765,
                778,
                767,
                781,
                768,
                783,
                770,
                784,
                774,
                785,
                773,
                787,
                755,
                791
            ],
            "class": "background"
        },
        {
            "polygon": [
                726,
                790,
                756,
                790,
                774,
                785,
                774,
                787,
                756,
                792,
                726,
                792
            ],
            "class": "curb"
        },
        {
            "polygon": [
                828,
                785,
                863,
                806,
                862,
                810,
                828,
                788
            ],
            "class": "curb"
        },
        {
            "polygon": [
                826,
                835,
                826,
                838,
                844,
                838,
                845,
                835
            ],
            "class": "crossWalk"
        },
        {
            "polygon": [
                799,
                831,
                799,
                836,
                819,
                836,
                819,
                831
            ],
            "class": "crossWalk"
        },
        {
            "polygon": [
                771,
                835,
                768,
                840,
                790,
                840,
                792,
                835
            ],
            "class": "crossWalk"
        },
        {
            "polygon": [
                766,
                834,
                768,
                830,
                749,
                830,
                745,
                834
            ],
            "class": "crossWalk"
        },
        {
            "polygon": [
                731,
                838,
                735,
                834,
                714,
                834,
                708,
                838
            ],
            "class": "crossWalk"
        },
        {
            "polygon": [
                692,
                833,
                713,
                833,
                717,
                830,
                697,
                830
            ],
            "class": "crossWalk"
        },
        {
            "polygon": [
                716,
                818,
                718,
                816,
                723,
                816,
                721,
                818
            ],
            "class": "roadMark"
        },
        {
            "polygon": [
                733,
                818,
                734,
                816,
                738,
                816,
                737,
                818
            ],
            "class": "roadMark"
        },
        {
            "polygon": [
                810,
                821,
                810,
                819,
                815,
                819,
                815,
                821
            ],
            "class": "roadMark"
        },
        {
            "polygon": [
                829,
                821,
                829,
                819,
                833,
                819,
                833,
                821
            ],
            "class": "roadMark"
        },
        {
            "polygon": [
                780,
                819,
                780,
                821,
                782,
                822,
                799,
                822,
                801,
                821,
                801,
                820,
                797,
                820,
                796,
                821,
                787,
                821,
                786,
                821,
                786,
                819
            ],
            "class": "roadMark"
        },
        {
            "polygon": [
                748,
                825,
                745,
                828,
                751,
                828,
                754,
                825
            ],
            "class": "whiteLane"
        },
        {
            "polygon": [
                755,
                820,
                757,
                818,
                762,
                818,
                760,
                820
            ],
            "class": "whiteLane"
        },
        {
            "polygon": [
                762,
                814,
                764,
                812,
                769,
                812,
                767,
                814
            ],
            "class": "whiteLane"
        },
        {
            "polygon": [
                768,
                810,
                770,
                808,
                774,
                808,
                772,
                810
            ],
            "class": "whiteLane"
        },
        {
            "polygon": [
                774,
                806,
                785,
                796,
                788,
                796,
                778,
                806
            ],
            "class": "whiteLane"
        },
        {
            "polygon": [
                690,
                818,
                703,
                818,
                701,
                820,
                706,
                820,
                710,
                816,
                692,
                816
            ],
            "class": "roadMark"
        },
        {
            "polygon": [
                726,
                801,
                739,
                796,
                743,
                796,
                731,
                801
            ],
            "class": "whiteLane"
        },
        {
            "polygon": [
                717,
                803,
                721,
                802,
                725,
                802,
                721,
                803
            ],
            "class": "whiteLane"
        },
        {
            "polygon": [
                786,
                744,
                792,
                744,
                792,
                746,
                786,
                746
            ],
            "class": "trafficLight"
        },
        {
            "polygon": [
                807,
                744,
                814,
                744,
                814,
                746,
                807,
                746
            ],
            "class": "trafficLight"
        },
        {
            "polygon": [
                835,
                798,
                838,
                798,
                850,
                810,
                849,
                812
            ],
            "class": "yellowLane"
        },
        {
            "polygon": [
                841,
                833,
                839,
                821,
                841,
                810,
                846,
                804,
                856,
                798,
                871,
                794,
                890,
                791,
                898,
                789,
                902,
                785,
                906,
                784,
                925,
                771,
                940,
                765,
                969,
                760,
                1008,
                761,
                1019,
                762,
                1028,
                761,
                1030,
                762,
                1030,
                764,
                1042,
                766,
                1067,
                773,
                1082,
                779,
                1092,
                781,
                1102,
                784,
                1106,
                789,
                1108,
                800,
                1109,
                822,
                1108,
                831,
                1104,
                834,
                1085,
                837,
                1080,
                845,
                1075,
                849,
                1070,
                851,
                1059,
                851,
                1052,
                847,
                1047,
                841,
                1026,
                841,
                1022,
                848,
                1016,
                852,
                1009,
                854,
                1000,
                854,
                992,
                851,
                986,
                843,
                949,
                843,
                945,
                847,
                939,
                850,
                931,
                850,
                925,
                848,
                918,
                843,
                887,
                843,
                883,
                849,
                878,
                852,
                864,
                852,
                857,
                847,
                854,
                842,
                846,
                842,
                843,
                840
            ],
            "class": "vehicle"
        },
        {
            "polygon": [
                1140,
                869,
                1160,
                864,
                1161,
                866,
                1141,
                871
            ],
            "class": "whiteLane"
        },
        {
            "polygon": [
                1164,
                801,
                1156,
                802,
                1151,
                807,
                1149,
                813,
                1149,
                820,
                1151,
                826,
                1155,
                830,
                1165,
                833
            ],
            "class": "bicycle"
        },
        {
            "polygon": [
                1181,
                884,
                1162,
                877,
                1157,
                873,
                1153,
                862,
                1154,
                840,
                1159,
                833,
                1161,
                790,
                1163,
                779,
                1168,
                768,
                1170,
                763,
                1175,
                761,
                1197,
                741,
                1196,
                732,
                1197,
                728,
                1201,
                725,
                1221,
                723,
                1253,
                719,
                1316,
                713,
                1391,
                711,
                1441,
                715,
                1477,
                725,
                1530,
                751,
                1553,
                764,
                1591,
                770,
                1624,
                779,
                1641,
                786,
                1651,
                795,
                1655,
                811,
                1658,
                834,
                1658,
                851,
                1659,
                854,
                1659,
                860,
                1653,
                866,
                1642,
                869,
                1639,
                869,
                1639,
                873,
                1637,
                875,
                1621,
                876,
                1618,
                884,
                1613,
                893,
                1604,
                900,
                1588,
                902,
                1569,
                901,
                1556,
                895,
                1547,
                880,
                1543,
                880,
                1536,
                887,
                1528,
                892,
                1512,
                892,
                1499,
                889,
                1487,
                881,
                1322,
                889,
                1320,
                894,
                1315,
                894,
                1316,
                889,
                1311,
                889,
                1308,
                902,
                1302,
                915,
                1294,
                923,
                1285,
                926,
                1259,
                927,
                1238,
                922,
                1225,
                913,
                1211,
                912,
                1199,
                907,
                1190,
                899
            ],
            "class": "vehicle"
        },
        {
            "polygon": [
                1711,
                806,
                1720,
                806,
                1721,
                749,
                1718,
                749,
                1717,
                801,
                1711,
                801
            ],
            "class": "background"
        }
    ]
}