{
    "information": {
        "filename": "12.jpg",
        "resolution": [
            1920,
            1080
        ]
    },
    "Scene_meta": {
        "zone": "세종-청사/시청 구간 (6-STOP)",
        "edge_case": [
            "대항차 전방 cutin 예측",
            "선행차 주행",
            "편향주행",
            "차로 변경",
            "횡단보도",
            "비보호 우회전"
        ],
        "scene_number": "08_150421_220615"
    },
    "Environment_meta": {
        "weather": "흐림",
        "date": "2022-06-15",
        "time": "15:04:21",
        "car_type": "G80",
        "traffic_Type": 0,
        "speed_type": 1,
        "road_type": "도심 3차로 이상"
    },
    "annotations": [
        {
            "polygon": [
                0,
                0,
                0,
                1080,
                1920,
                1080,
                1920,
                0
            ],
            "class": "background"
        },
        {
            "polygon": [
                0,
                916,
                220,
                947,
                305,
                947,
                325,
                946,
                520,
                945,
                594,
                945,
                618,
                944,
                740,
                936,
                989,
                917,
                1216,
                897,
                1483,
                868,
                1647,
                846,
                1775,
                824,
                1920,
                810,
                1920,
                1080,
                0,
                1080
            ],
            "class": "freespace"
        },
        {
            "polygon": [
                284,
                915,
                303,
                913,
                316,
                915,
                323,
                916,
                336,
                913,
                347,
                912,
                368,
                914,
                376,
                916,
                388,
                913,
                397,
                915,
                404,
                916,
                412,
                916,
                418,
                911,
                427,
                911,
                437,
                912,
                451,
                913,
                465,
                914,
                471,
                911,
                477,
                906,
                484,
                902,
                485,
                900,
                389,
                897,
                284,
                894
            ],
            "class": "sideWalk"
        },
        {
            "polygon": [
                668,
                896,
                804,
                891,
                976,
                884,
                1122,
                873,
                1221,
                865,
                1465,
                842,
                1535,
                834,
                1536,
                840,
                1540,
                847,
                1537,
                848,
                1507,
                850,
                1487,
                852,
                1470,
                854,
                1454,
                856,
                1443,
                857,
                1434,
                860,
                1434,
                862,
                1440,
                863,
                1448,
                863,
                1460,
                862,
                1472,
                861,
                1486,
                862,
                1298,
                886,
                1283,
                881,
                1249,
                879,
                1168,
                884,
                1119,
                888,
                1078,
                891,
                1053,
                895,
                1030,
                898,
                1019,
                898,
                1011,
                898,
                999,
                899,
                999,
                901,
                1006,
                902,
                1021,
                903,
                1031,
                905,
                1053,
                907,
                852,
                925,
                738,
                934,
                722,
                924,
                712,
                917,
                702,
                914,
                691,
                913,
                685,
                914,
                673,
                909,
                670,
                904
            ],
            "class": "sideWalk"
        },
        {
            "polygon": [
                620,
                944,
                696,
                934,
                717,
                931,
                767,
                923,
                933,
                912,
                1106,
                900,
                1265,
                885,
                1424,
                870,
                1604,
                847,
                1750,
                826,
                1752,
                836,
                1678,
                849,
                1504,
                871,
                1258,
                900,
                1064,
                919,
                946,
                926,
                802,
                935,
                717,
                940
            ],
            "class": "curb"
        },
        {
            "polygon": [
                324,
                889,
                324,
                905,
                324,
                914,
                332,
                914,
                333,
                896,
                332,
                890,
                442,
                889,
                442,
                910,
                449,
                911,
                449,
                885
            ],
            "class": "background"
        },
        {
            "polygon": [
                379,
                882,
                381,
                922,
                384,
                923,
                382,
                883,
                389,
                882,
                393,
                940,
                396,
                939,
                392,
                878
            ],
            "class": "background"
        },
        {
            "polygon": [
                321,
                914,
                357,
                916,
                356,
                948,
                321,
                948
            ],
            "class": "rubberCone"
        },
        {
            "polygon": [
                662,
                853,
                656,
                898,
                666,
                902,
                671,
                907,
                676,
                908,
                684,
                908,
                688,
                907,
                684,
                905,
                676,
                901,
                667,
                853
            ],
            "class": "rubberCone"
        },
        {
            "polygon": [
                733,
                856,
                727,
                910,
                717,
                912,
                722,
                914,
                734,
                915,
                748,
                914,
                756,
                913,
                757,
                911,
                747,
                910,
                738,
                856
            ],
            "class": "rubberCone"
        },
        {
            "polygon": [
                650,
                856,
                715,
                861,
                735,
                862,
                735,
                839,
                738,
                839,
                739,
                863,
                740,
                869,
                738,
                871,
                739,
                923,
                737,
                923,
                736,
                870,
                718,
                870,
                676,
                873,
                655,
                874,
                655,
                869,
                676,
                867,
                658,
                864,
                652,
                863
            ],
            "class": "background"
        },
        {
            "polygon": [
                826,
                916,
                877,
                913,
                880,
                915,
                881,
                914,
                929,
                910,
                950,
                923,
                950,
                928,
                902,
                932,
                848,
                934,
                827,
                933,
                824,
                929,
                823,
                924
            ],
            "class": "background"
        },
        {
            "polygon": [
                806,
                875,
                801,
                933,
                794,
                935,
                794,
                937,
                809,
                938,
                828,
                936,
                833,
                935,
                833,
                933,
                823,
                931,
                820,
                917,
                812,
                874
            ],
            "class": "rubberCone"
        },
        {
            "polygon": [
                1042,
                870,
                1042,
                877,
                1044,
                878,
                1044,
                899,
                1064,
                899,
                1065,
                878,
                1091,
                869,
                1091,
                894,
                1106,
                894,
                1102,
                869,
                1160,
                866,
                1160,
                888,
                1185,
                887,
                1184,
                860
            ],
            "class": "background"
        },
        {
            "polygon": [
                1497,
                831,
                1496,
                842,
                1493,
                854,
                1512,
                853,
                1511,
                844,
                1509,
                830
            ],
            "class": "background"
        },
        {
            "polygon": [
                1611,
                859,
                1597,
                861,
                1584,
                863,
                1568,
                865,
                1546,
                868,
                1545,
                869,
                1552,
                869,
                1566,
                868,
                1583,
                866,
                1591,
                866,
                1601,
                864,
                1616,
                860
            ],
            "class": "roadMark"
        },
        {
            "polygon": [
                1689,
                848,
                1675,
                850,
                1658,
                853,
                1649,
                854,
                1653,
                854,
                1659,
                854,
                1668,
                853,
                1679,
                852,
                1687,
                851,
                1693,
                849
            ],
            "class": "roadMark"
        },
        {
            "polygon": [
                1391,
                887,
                1248,
                906,
                1417,
                889,
                1415,
                888,
                1489,
                880,
                1487,
                877,
                1401,
                888
            ],
            "class": "roadMark"
        },
        {
            "polygon": [
                1507,
                885,
                1411,
                900,
                1541,
                887,
                1540,
                885,
                1659,
                868,
                1653,
                866,
                1522,
                885
            ],
            "class": "roadMark"
        },
        {
            "polygon": [
                1812,
                854,
                1711,
                873,
                1646,
                884,
                1646,
                886,
                1648,
                887,
                1631,
                891,
                1722,
                881,
                1722,
                876,
                1693,
                881,
                1690,
                881,
                1688,
                879,
                1818,
                856
            ],
            "class": "roadMark"
        },
        {
            "polygon": [
                1484,
                902,
                1688,
                872,
                1751,
                862,
                1751,
                859,
                1625,
                880,
                1463,
                903
            ],
            "class": "whiteLane"
        },
        {
            "polygon": [
                1257,
                914,
                1564,
                875,
                1683,
                859,
                1682,
                855,
                1474,
                884,
                1240,
                914
            ],
            "class": "whiteLane"
        },
        {
            "polygon": [
                1079,
                919,
                1217,
                915,
                1347,
                907,
                1503,
                902,
                1569,
                899,
                1694,
                894,
                1671,
                900,
                1613,
                900,
                1440,
                907,
                1285,
                915,
                1195,
                918,
                1040,
                923
            ],
            "class": "stopLane"
        },
        {
            "polygon": [
                1475,
                933,
                1756,
                883,
                1920,
                847,
                1920,
                850,
                1679,
                901,
                1491,
                934
            ],
            "class": "yellowLane"
        },
        {
            "polygon": [
                1508,
                934,
                1668,
                905,
                1833,
                871,
                1920,
                852,
                1920,
                857,
                1667,
                907,
                1528,
                934
            ],
            "class": "yellowLane"
        },
        {
            "polygon": [
                1676,
                759,
                1679,
                757,
                1679,
                753,
                1680,
                751,
                1678,
                748,
                1675,
                747,
                1672,
                748,
                1669,
                751,
                1668,
                754,
                1669,
                757,
                1664,
                762,
                1663,
                767,
                1663,
                773,
                1667,
                773,
                1684,
                769,
                1683,
                765,
                1680,
                763,
                1678,
                761
            ],
            "class": "rider"
        },
        {
            "polygon": [
                1754,
                755,
                1706,
                759,
                1680,
                765,
                1667,
                772,
                1646,
                794,
                1619,
                802,
                1600,
                813,
                1598,
                818,
                1597,
                823,
                1598,
                828,
                1596,
                833,
                1595,
                837,
                1596,
                848,
                1602,
                850,
                1605,
                857,
                1610,
                862,
                1618,
                863,
                1625,
                861,
                1629,
                859,
                1632,
                855,
                1634,
                850,
                1666,
                848,
                1680,
                847,
                1683,
                848,
                1687,
                848,
                1689,
                852,
                1694,
                854,
                1700,
                854,
                1707,
                854,
                1714,
                852,
                1719,
                850,
                1724,
                846,
                1727,
                840,
                1753,
                836,
                1813,
                802,
                1814,
                787,
                1809,
                780,
                1799,
                775,
                1793,
                773,
                1782,
                764,
                1776,
                759,
                1765,
                757
            ],
            "class": "vehicle"
        },
        {
            "polygon": [
                1702,
                790,
                1700,
                892,
                1693,
                894,
                1691,
                898,
                1698,
                899,
                1717,
                896,
                1719,
                894,
                1715,
                893,
                1711,
                890,
                1714,
                790
            ],
            "class": "background"
        },
        {
            "polygon": [
                1745,
                785,
                1745,
                883,
                1739,
                886,
                1736,
                889,
                1741,
                890,
                1750,
                890,
                1761,
                889,
                1766,
                887,
                1768,
                885,
                1764,
                884,
                1762,
                883,
                1761,
                860,
                1835,
                847,
                1835,
                866,
                1831,
                870,
                1834,
                872,
                1844,
                871,
                1852,
                869,
                1854,
                868,
                1853,
                866,
                1849,
                865,
                1849,
                843,
                1911,
                832,
                1910,
                849,
                1905,
                854,
                1907,
                855,
                1912,
                855,
                1920,
                853,
                1920,
                763,
                1909,
                764,
                1910,
                775,
                1849,
                782,
                1849,
                772,
                1835,
                774,
                1834,
                785,
                1760,
                794,
                1760,
                782
            ],
            "class": "fense"
        },
        {
            "polygon": [
                1920,
                936,
                1784,
                982,
                1850,
                982,
                1920,
                956
            ],
            "class": "crossWalk"
        },
        {
            "polygon": [
                1832,
                993,
                1695,
                1040,
                1575,
                1080,
                1673,
                1080,
                1811,
                1030,
                1901,
                992
            ],
            "class": "crossWalk"
        },
        {
            "polygon": [
                1345,
                1070,
                1508,
                1031,
                1652,
                993,
                1718,
                995,
                1572,
                1036,
                1423,
                1078
            ],
            "class": "crossWalk"
        },
        {
            "polygon": [
                1612,
                982,
                1731,
                952,
                1808,
                929,
                1860,
                929,
                1770,
                959,
                1677,
                982
            ],
            "class": "crossWalk"
        },
        {
            "polygon": [
                1668,
                931,
                1584,
                951,
                1458,
                979,
                1515,
                982,
                1617,
                957,
                1720,
                931
            ],
            "class": "crossWalk"
        },
        {
            "polygon": [
                1484,
                991,
                1339,
                1021,
                1155,
                1055,
                1222,
                1062,
                1364,
                1031,
                1544,
                992
            ],
            "class": "crossWalk"
        },
        {
            "polygon": [
                1328,
                985,
                1179,
                1010,
                994,
                1037,
                1053,
                1042,
                1202,
                1019,
                1383,
                989
            ],
            "class": "crossWalk"
        },
        {
            "polygon": [
                1465,
                948,
                1311,
                974,
                1367,
                977,
                1516,
                949
            ],
            "class": "crossWalk"
        },
        {
            "polygon": [
                1425,
                932,
                1318,
                949,
                1186,
                968,
                1232,
                972,
                1343,
                954,
                1470,
                934
            ],
            "class": "crossWalk"
        },
        {
            "polygon": [
                1189,
                979,
                1027,
                1001,
                864,
                1019,
                910,
                1028,
                1061,
                1008,
                1244,
                981
            ],
            "class": "crossWalk"
        },
        {
            "polygon": [
                1069,
                964,
                1207,
                949,
                1314,
                934,
                1352,
                934,
                1229,
                951,
                1111,
                966
            ],
            "class": "crossWalk"
        },
        {
            "polygon": [
                1075,
                970,
                936,
                988,
                756,
                1005,
                790,
                1010,
                961,
                993,
                1118,
                975
            ],
            "class": "crossWalk"
        },
        {
            "polygon": [
                973,
                961,
                1008,
                963,
                1116,
                951,
                1247,
                936,
                1215,
                935,
                1118,
                946
            ],
            "class": "crossWalk"
        },
        {
            "polygon": [
                880,
                959,
                916,
                960,
                1049,
                948,
                1150,
                938,
                1121,
                936,
                1022,
                945
            ],
            "class": "crossWalk"
        },
        {
            "polygon": [
                652,
                993,
                692,
                998,
                854,
                986,
                1005,
                970,
                969,
                967,
                863,
                977
            ],
            "class": "crossWalk"
        },
        {
            "polygon": [
                574,
                985,
                610,
                989,
                738,
                979,
                905,
                966,
                870,
                965,
                737,
                975
            ],
            "class": "crossWalk"
        },
        {
            "polygon": [
                496,
                975,
                534,
                980,
                674,
                973,
                820,
                962,
                789,
                960,
                670,
                968
            ],
            "class": "crossWalk"
        },
        {
            "polygon": [
                801,
                955,
                828,
                957,
                1060,
                937,
                1031,
                937,
                938,
                944
            ],
            "class": "crossWalk"
        },
        {
            "polygon": [
                908,
                942,
                936,
                942,
                985,
                937,
                957,
                936
            ],
            "class": "crossWalk"
        },
        {
            "polygon": [
                732,
                953,
                757,
                955,
                835,
                948,
                821,
                948
            ],
            "class": "crossWalk"
        },
        {
            "polygon": [
                675,
                951,
                691,
                952,
                811,
                945,
                910,
                937,
                875,
                937,
                789,
                944
            ],
            "class": "crossWalk"
        },
        {
            "polygon": [
                629,
                951,
                723,
                946,
                811,
                941,
                798,
                940,
                611,
                949
            ],
            "class": "crossWalk"
        },
        {
            "polygon": [
                531,
                947,
                563,
                949,
                647,
                946,
                787,
                939,
                779,
                938,
                659,
                943,
                593,
                946
            ],
            "class": "crossWalk"
        },
        {
            "polygon": [
                441,
                969,
                472,
                973,
                560,
                968,
                742,
                959,
                712,
                956,
                599,
                963
            ],
            "class": "crossWalk"
        },
        {
            "polygon": [
                414,
                963,
                450,
                965,
                558,
                960,
                671,
                955,
                635,
                954,
                533,
                958
            ],
            "class": "crossWalk"
        },
        {
            "polygon": [
                354,
                959,
                377,
                960,
                473,
                958,
                609,
                952,
                593,
                950,
                473,
                955
            ],
            "class": "crossWalk"
        },
        {
            "polygon": [
                513,
                950,
                512,
                951,
                507,
                952,
                520,
                952,
                532,
                952,
                538,
                951,
                535,
                951,
                526,
                951,
                520,
                949
            ],
            "class": "roadMark"
        },
        {
            "polygon": [
                340,
                953,
                353,
                953,
                370,
                954,
                370,
                955,
                366,
                956,
                359,
                956,
                350,
                956,
                341,
                955
            ],
            "class": "roadMark"
        },
        {
            "polygon": [
                216,
                1015,
                223,
                1012,
                354,
                1018,
                356,
                1021
            ],
            "class": "whiteLane"
        },
        {
            "polygon": [
                230,
                1068,
                244,
                1073,
                439,
                1058,
                428,
                1054
            ],
            "class": "whiteLane"
        },
        {
            "polygon": [
                0,
                997,
                115,
                1008,
                124,
                1006,
                6,
                995
            ],
            "class": "whiteLane"
        },
        {
            "polygon": [
                0,
                764,
                19,
                759,
                58,
                758,
                129,
                758,
                213,
                766,
                240,
                773,
                266,
                778,
                272,
                781,
                271,
                784,
                266,
                786,
                267,
                799,
                278,
                818,
                286,
                823,
                291,
                828,
                291,
                870,
                295,
                878,
                298,
                886,
                290,
                918,
                286,
                926,
                269,
                931,
                255,
                937,
                245,
                938,
                233,
                939,
                220,
                958,
                201,
                966,
                182,
                968,
                165,
                966,
                155,
                961,
                143,
                957,
                133,
                955,
                126,
                950,
                121,
                943,
                18,
                942,
                0,
                942
            ],
            "class": "vehicle"
        },
        {
            "polygon": [
                1811,
                119,
                1817,
                115,
                1826,
                115,
                1833,
                115,
                1846,
                110,
                1852,
                104,
                1861,
                103,
                1868,
                104,
                1886,
                97,
                1893,
                91,
                1900,
                89,
                1908,
                89,
                1914,
                90,
                1920,
                86,
                1920,
                135,
                1786,
                176,
                1785,
                165,
                1777,
                162,
                1770,
                157,
                1768,
                151,
                1768,
                143,
                1770,
                135,
                1775,
                129,
                1780,
                127,
                1788,
                126,
                1794,
                126
            ],
            "class": "trafficLight"
        }
    ]
}