{
    "information": {
        "filename": "39.jpg",
        "resolution": [
            1920,
            1080
        ]
    },
    "Scene_meta": {
        "zone": "세종-청사/시청 구간 (6-STOP)",
        "edge_case": [
            "대항차 전방 cutin 예측",
            "선행차 주행",
            "편향주행",
            "차로 변경",
            "횡단보도",
            "비보호 우회전"
        ],
        "scene_number": "08_150421_220615"
    },
    "Environment_meta": {
        "weather": "흐림",
        "date": "2022-06-15",
        "time": "15:04:21",
        "car_type": "G80",
        "traffic_Type": 0,
        "speed_type": 1,
        "road_type": "도심 3차로 이상"
    },
    "annotations": [
        {
            "polygon": [
                0,
                0,
                1920,
                0,
                1920,
                1080,
                0,
                1080
            ],
            "class": "background"
        },
        {
            "polygon": [
                331,
                842,
                364,
                837,
                478,
                830,
                477,
                845,
                457,
                845,
                430,
                845,
                398,
                846,
                367,
                847,
                346,
                848,
                340,
                847
            ],
            "class": "freespace"
        },
        {
            "polygon": [
                309,
                823,
                356,
                821,
                380,
                818,
                424,
                815,
                424,
                822,
                420,
                826,
                423,
                831,
                380,
                836,
                351,
                839,
                331,
                842,
                318,
                836,
                310,
                829,
                308,
                826
            ],
            "class": "sideWalk"
        },
        {
            "polygon": [
                351,
                839,
                372,
                834,
                421,
                829,
                474,
                824,
                474,
                830,
                380,
                838
            ],
            "class": "curb"
        },
        {
            "polygon": [
                407,
                811,
                407,
                829,
                414,
                829,
                414,
                808,
                457,
                809,
                459,
                849,
                469,
                850,
                468,
                808,
                473,
                814,
                472,
                824,
                472,
                828,
                472,
                833,
                473,
                839,
                475,
                844,
                478,
                848,
                487,
                845,
                493,
                826,
                485,
                804,
                475,
                793,
                437,
                794,
                421,
                799
            ],
            "class": "background"
        },
        {
            "polygon": [
                598,
                810,
                626,
                806,
                634,
                803,
                622,
                802,
                622,
                794,
                641,
                795,
                672,
                797,
                682,
                796,
                697,
                793,
                707,
                787,
                727,
                788,
                743,
                785,
                755,
                783,
                763,
                780,
                779,
                781,
                841,
                782,
                883,
                795,
                904,
                797,
                1024,
                831,
                1060,
                835,
                1136,
                840,
                1177,
                840,
                1302,
                839,
                1393,
                834,
                1465,
                827,
                1694,
                812,
                1863,
                797,
                1920,
                790,
                1920,
                810,
                1529,
                889,
                1522,
                897,
                1800,
                980,
                1920,
                1004,
                1920,
                1080,
                200,
                1080,
                681,
                850,
                687,
                840,
                681,
                837,
                654,
                834,
                623,
                835,
                615,
                830,
                614,
                821,
                611,
                816,
                606,
                815,
                603,
                815,
                599,
                812
            ],
            "class": "freespace"
        },
        {
            "polygon": [
                412,
                700,
                410,
                717,
                410,
                724,
                417,
                726,
                417,
                718,
                413,
                700
            ],
            "class": "trafficSign"
        },
        {
            "polygon": [
                410,
                726,
                406,
                740,
                406,
                749,
                417,
                748,
                417,
                741,
                411,
                726
            ],
            "class": "trafficSign"
        },
        {
            "polygon": [
                0,
                875,
                31,
                872,
                51,
                1080,
                0,
                1080
            ],
            "class": "fense"
        },
        {
            "polygon": [
                109,
                1080,
                462,
                938,
                624,
                869,
                687,
                840,
                688,
                852,
                688,
                855,
                498,
                955,
                254,
                1080
            ],
            "class": "curb"
        },
        {
            "polygon": [
                109,
                875,
                111,
                1080,
                142,
                1080,
                134,
                874
            ],
            "class": "background"
        },
        {
            "polygon": [
                623,
                835,
                645,
                828,
                733,
                840,
                707,
                855,
                688,
                852,
                687,
                840,
                681,
                837,
                654,
                834
            ],
            "class": "safetyZone"
        },
        {
            "polygon": [
                620,
                833,
                733,
                801,
                736,
                802,
                623,
                835
            ],
            "class": "yellowLane"
        },
        {
            "polygon": [
                732,
                839,
                621,
                906,
                329,
                1080,
                367,
                1080,
                737,
                840
            ],
            "class": "yellowLane"
        },
        {
            "polygon": [
                647,
                826,
                737,
                840,
                736,
                841,
                644,
                828
            ],
            "class": "yellowLane"
        },
        {
            "polygon": [
                657,
                801,
                667,
                801,
                669,
                804,
                662,
                804
            ],
            "class": "crossWalk"
        },
        {
            "polygon": [
                676,
                800,
                686,
                800,
                690,
                803,
                680,
                803
            ],
            "class": "crossWalk"
        },
        {
            "polygon": [
                696,
                800,
                705,
                799,
                704,
                800,
                709,
                800,
                708,
                802,
                701,
                802,
                701,
                801,
                696,
                802
            ],
            "class": "crossWalk"
        },
        {
            "polygon": [
                715,
                798,
                722,
                798,
                722,
                799,
                727,
                799,
                727,
                801,
                718,
                801,
                714,
                800
            ],
            "class": "crossWalk"
        },
        {
            "polygon": [
                734,
                797,
                734,
                799,
                738,
                799,
                738,
                801,
                747,
                801,
                747,
                798,
                739,
                798,
                739,
                797
            ],
            "class": "crossWalk"
        },
        {
            "polygon": [
                751,
                797,
                751,
                799,
                765,
                799,
                766,
                796
            ],
            "class": "crossWalk"
        },
        {
            "polygon": [
                778,
                796,
                770,
                796,
                770,
                798,
                777,
                798
            ],
            "class": "crossWalk"
        },
        {
            "polygon": [
                779,
                797,
                779,
                798,
                786,
                798,
                786,
                797
            ],
            "class": "crossWalk"
        },
        {
            "polygon": [
                744,
                803,
                738,
                804,
                737,
                805,
                742,
                804,
                748,
                805,
                750,
                805,
                750,
                803
            ],
            "class": "roadMark"
        },
        {
            "polygon": [
                756,
                802,
                754,
                804,
                758,
                805,
                759,
                804,
                759,
                802
            ],
            "class": "roadMark"
        },
        {
            "polygon": [
                762,
                803,
                761,
                805,
                764,
                805,
                765,
                803
            ],
            "class": "roadMark"
        },
        {
            "polygon": [
                776,
                801,
                770,
                801,
                769,
                803,
                772,
                803,
                776,
                804,
                780,
                804,
                782,
                802,
                782,
                801
            ],
            "class": "roadMark"
        },
        {
            "polygon": [
                746,
                808,
                736,
                809,
                737,
                810,
                745,
                811,
                751,
                810,
                754,
                811,
                757,
                810,
                758,
                809,
                748,
                809
            ],
            "class": "roadMark"
        },
        {
            "polygon": [
                710,
                822,
                691,
                824,
                702,
                825,
                709,
                824,
                711,
                825,
                712,
                826,
                719,
                826,
                722,
                824,
                717,
                823,
                714,
                825
            ],
            "class": "roadMark"
        },
        {
            "polygon": [
                808,
                821,
                798,
                824,
                804,
                824,
                803,
                826,
                810,
                826,
                810,
                824,
                817,
                824
            ],
            "class": "roadMark"
        },
        {
            "polygon": [
                807,
                865,
                788,
                872,
                799,
                873,
                799,
                877,
                772,
                877,
                774,
                875,
                728,
                879,
                770,
                883,
                771,
                880,
                798,
                880,
                798,
                884,
                811,
                884,
                812,
                874,
                829,
                872
            ],
            "class": "roadMark"
        },
        {
            "polygon": [
                900,
                820,
                904,
                825,
                914,
                825,
                938,
                824,
                918,
                821,
                918,
                823,
                906,
                823,
                905,
                820
            ],
            "class": "roadMark"
        },
        {
            "polygon": [
                791,
                799,
                787,
                802,
                791,
                803,
                795,
                800
            ],
            "class": "whiteLane"
        },
        {
            "polygon": [
                785,
                804,
                784,
                806,
                787,
                806,
                788,
                804
            ],
            "class": "whiteLane"
        },
        {
            "polygon": [
                781,
                807,
                780,
                809,
                784,
                809,
                785,
                807
            ],
            "class": "whiteLane"
        },
        {
            "polygon": [
                776,
                811,
                774,
                813,
                778,
                813,
                780,
                811
            ],
            "class": "whiteLane"
        },
        {
            "polygon": [
                769,
                814,
                768,
                817,
                773,
                817,
                773,
                814
            ],
            "class": "whiteLane"
        },
        {
            "polygon": [
                762,
                819,
                758,
                822,
                764,
                822,
                768,
                819
            ],
            "class": "whiteLane"
        },
        {
            "polygon": [
                755,
                824,
                748,
                828,
                753,
                828,
                759,
                825
            ],
            "class": "whiteLane"
        },
        {
            "polygon": [
                741,
                834,
                735,
                838,
                741,
                838,
                748,
                834
            ],
            "class": "whiteLane"
        },
        {
            "polygon": [
                841,
                797,
                845,
                806,
                850,
                805,
                844,
                797
            ],
            "class": "whiteLane"
        },
        {
            "polygon": [
                846,
                807,
                851,
                807,
                851,
                809,
                846,
                809
            ],
            "class": "whiteLane"
        },
        {
            "polygon": [
                849,
                810,
                853,
                810,
                853,
                812,
                849,
                812
            ],
            "class": "whiteLane"
        },
        {
            "polygon": [
                851,
                813,
                855,
                813,
                856,
                815,
                851,
                815
            ],
            "class": "whiteLane"
        },
        {
            "polygon": [
                853,
                817,
                858,
                817,
                860,
                820,
                853,
                820
            ],
            "class": "whiteLane"
        },
        {
            "polygon": [
                857,
                824,
                863,
                824,
                864,
                828,
                857,
                828
            ],
            "class": "whiteLane"
        },
        {
            "polygon": [
                861,
                832,
                868,
                832,
                872,
                836,
                863,
                837
            ],
            "class": "whiteLane"
        },
        {
            "polygon": [
                868,
                841,
                876,
                841,
                880,
                846,
                871,
                846
            ],
            "class": "whiteLane"
        },
        {
            "polygon": [
                877,
                857,
                888,
                857,
                894,
                866,
                882,
                866
            ],
            "class": "whiteLane"
        },
        {
            "polygon": [
                896,
                884,
                908,
                884,
                918,
                899,
                904,
                898
            ],
            "class": "whiteLane"
        },
        {
            "polygon": [
                927,
                934,
                945,
                933,
                971,
                969,
                951,
                969
            ],
            "class": "whiteLane"
        },
        {
            "polygon": [
                1027,
                1080,
                1024,
                1077,
                1058,
                1076,
                1065,
                1080
            ],
            "class": "whiteLane"
        },
        {
            "polygon": [
                903,
                801,
                998,
                837,
                1000,
                836,
                905,
                800
            ],
            "class": "yellowLane"
        },
        {
            "polygon": [
                1413,
                929,
                1431,
                929,
                1449,
                941,
                1506,
                963,
                1554,
                979,
                1621,
                993,
                1769,
                1026,
                1920,
                1059,
                1920,
                1073,
                1724,
                1028,
                1603,
                1000,
                1532,
                981,
                1477,
                964,
                1435,
                947,
                1420,
                938
            ],
            "class": "yellowLane"
        },
        {
            "polygon": [
                1478,
                872,
                1667,
                856,
                1668,
                853,
                1468,
                869
            ],
            "class": "crossWalk"
        },
        {
            "polygon": [
                1446,
                867,
                1651,
                852,
                1651,
                849,
                1436,
                865
            ],
            "class": "crossWalk"
        },
        {
            "polygon": [
                1415,
                862,
                1671,
                846,
                1672,
                843,
                1408,
                860
            ],
            "class": "crossWalk"
        },
        {
            "polygon": [
                1388,
                860,
                1670,
                840,
                1669,
                838,
                1379,
                858
            ],
            "class": "crossWalk"
        },
        {
            "polygon": [
                1360,
                856,
                1516,
                846,
                1668,
                837,
                1669,
                834,
                1559,
                841,
                1349,
                853
            ],
            "class": "crossWalk"
        },
        {
            "polygon": [
                1341,
                852,
                1394,
                849,
                1537,
                841,
                1620,
                835,
                1620,
                833,
                1484,
                842,
                1315,
                851
            ],
            "class": "crossWalk"
        },
        {
            "polygon": [
                1248,
                842,
                1310,
                848,
                1408,
                843,
                1585,
                834,
                1489,
                830,
                1354,
                837
            ],
            "class": "crossWalk"
        },
        {
            "polygon": [
                1051,
                782,
                1066,
                783,
                1066,
                785,
                1063,
                788,
                1064,
                790,
                1081,
                790,
                1102,
                790,
                1142,
                794,
                1241,
                799,
                1323,
                800,
                1344,
                799,
                1464,
                804,
                1557,
                797,
                1621,
                791,
                1681,
                786,
                1814,
                761,
                1838,
                755,
                1838,
                751,
                1837,
                738,
                1902,
                733,
                1904,
                766,
                1903,
                769,
                1889,
                773,
                1857,
                775,
                1833,
                777,
                1802,
                788,
                1671,
                813,
                1393,
                834,
                1303,
                839,
                1176,
                840,
                1138,
                840,
                1104,
                834,
                1102,
                823,
                1064,
                820,
                1063,
                812,
                1064,
                804,
                1063,
                798,
                1061,
                797,
                1051,
                795
            ],
            "class": "sideWalk"
        },
        {
            "polygon": [
                1054,
                770,
                1054,
                815,
                1059,
                815,
                1060,
                772,
                1090,
                775,
                1091,
                828,
                1103,
                828,
                1101,
                769
            ],
            "class": "background"
        },
        {
            "polygon": [
                901,
                795,
                1018,
                826,
                1034,
                830,
                1107,
                830,
                1139,
                840,
                1032,
                837,
                1020,
                836,
                964,
                817,
                902,
                798
            ],
            "class": "curb"
        },
        {
            "polygon": [
                907,
                776,
                939,
                778,
                1051,
                775,
                1052,
                827,
                1049,
                827,
                1048,
                819,
                1042,
                818,
                1043,
                825,
                1040,
                824,
                1039,
                818,
                1035,
                817,
                1035,
                824,
                1033,
                824,
                1032,
                817,
                1026,
                816,
                1027,
                822,
                1023,
                822,
                1023,
                816,
                1019,
                815,
                1019,
                820,
                1017,
                820,
                1017,
                815,
                1013,
                814,
                1013,
                819,
                1009,
                818,
                1009,
                813,
                1007,
                813,
                1007,
                817,
                1004,
                817,
                1004,
                813,
                1001,
                812,
                1001,
                818,
                907,
                794
            ],
            "class": "fense"
        },
        {
            "polygon": [
                1920,
                765,
                1881,
                771,
                1834,
                776,
                1806,
                783,
                1804,
                790,
                1805,
                796,
                1816,
                800,
                1920,
                791
            ],
            "class": "background"
        },
        {
            "polygon": [
                1176,
                840,
                1213,
                831,
                1257,
                830,
                1308,
                839,
                1237,
                841
            ],
            "class": "curb"
        },
        {
            "polygon": [
                1394,
                834,
                1434,
                825,
                1592,
                815,
                1734,
                806,
                1834,
                795,
                1920,
                787,
                1920,
                795,
                1745,
                813,
                1665,
                818,
                1513,
                829,
                1448,
                832
            ],
            "class": "curb"
        },
        {
            "polygon": [
                1920,
                802,
                1783,
                825,
                1643,
                865,
                1552,
                884,
                1519,
                887,
                1511,
                891,
                1510,
                896,
                1512,
                903,
                1529,
                924,
                1920,
                1003
            ],
            "class": "sideWalk"
        },
        {
            "polygon": [
                1512,
                904,
                1529,
                914,
                1581,
                929,
                1743,
                957,
                1920,
                982,
                1920,
                1030,
                1664,
                982,
                1567,
                958,
                1525,
                943,
                1518,
                939,
                1510,
                922,
                1510,
                897
            ],
            "class": "curb"
        },
        {
            "polygon": [
                1587,
                769,
                1590,
                812,
                1594,
                812,
                1592,
                769,
                1611,
                766,
                1616,
                886,
                1607,
                889,
                1604,
                898,
                1606,
                905,
                1611,
                908,
                1621,
                909,
                1623,
                932,
                1629,
                933,
                1627,
                910,
                1646,
                905,
                1646,
                898,
                1671,
                895,
                1671,
                914,
                1699,
                912,
                1829,
                893,
                1807,
                753,
                1663,
                768,
                1670,
                888,
                1644,
                893,
                1642,
                890,
                1638,
                890,
                1633,
                751,
                1584,
                752
            ],
            "class": "background"
        },
        {
            "polygon": [
                1843,
                702,
                1816,
                784,
                1819,
                784,
                1842,
                721,
                1845,
                721,
                1848,
                779,
                1853,
                779,
                1850,
                716,
                1887,
                777,
                1891,
                776,
                1851,
                709
            ],
            "class": "background"
        },
        {
            "polygon": [
                1637,
                610,
                1705,
                940,
                1710,
                938,
                1705,
                912,
                1828,
                893,
                1836,
                917,
                1849,
                913,
                1772,
                598
            ],
            "class": "constructionGuide"
        },
        {
            "polygon": [
                1581,
                655,
                1571,
                683,
                1571,
                693,
                1599,
                689,
                1599,
                681,
                1584,
                655
            ],
            "class": "trafficSign"
        },
        {
            "polygon": [
                1635,
                439,
                1602,
                520,
                1607,
                548,
                1693,
                540,
                1693,
                511,
                1641,
                437
            ],
            "class": "trafficSign"
        },
        {
            "polygon": [
                1098,
                669,
                1084,
                693,
                1084,
                702,
                1112,
                704,
                1113,
                694,
                1100,
                669
            ],
            "class": "trafficSign"
        },
        {
            "polygon": [
                809,
                704,
                809,
                709,
                833,
                709,
                833,
                704
            ],
            "class": "trafficLight"
        },
        {
            "polygon": [
                858,
                702,
                883,
                702,
                883,
                709,
                858,
                709
            ],
            "class": "trafficLight"
        },
        {
            "polygon": [
                833,
                718,
                853,
                717,
                853,
                724,
                833,
                724
            ],
            "class": "trafficLight"
        },
        {
            "polygon": [
                855,
                716,
                855,
                721,
                856,
                722,
                858,
                724,
                862,
                723,
                864,
                721,
                864,
                718,
                863,
                715,
                861,
                714,
                859,
                714
            ],
            "class": "trafficSign"
        },
        {
            "polygon": [
                835,
                756,
                845,
                756,
                851,
                759,
                852,
                776,
                844,
                788,
                842,
                789,
                833,
                789,
                829,
                779,
                830,
                758
            ],
            "class": "bus"
        },
        {
            "polygon": [
                698,
                759,
                700,
                757,
                710,
                755,
                717,
                757,
                723,
                760,
                727,
                768,
                728,
                791,
                726,
                793,
                723,
                794,
                719,
                794,
                719,
                791,
                707,
                791,
                705,
                795,
                698,
                795,
                696,
                792,
                694,
                785,
                693,
                773,
                691,
                772,
                691,
                770,
                693,
                768,
                693,
                762
            ],
            "class": "bus"
        },
        {
            "polygon": [
                774,
                768,
                790,
                768,
                794,
                772,
                796,
                780,
                797,
                777,
                799,
                775,
                802,
                775,
                805,
                771,
                816,
                770,
                825,
                770,
                830,
                772,
                832,
                778,
                834,
                781,
                834,
                788,
                835,
                790,
                835,
                809,
                834,
                811,
                829,
                811,
                828,
                810,
                828,
                807,
                797,
                807,
                797,
                809,
                796,
                811,
                792,
                811,
                790,
                809,
                791,
                791,
                789,
                788,
                776,
                788,
                776,
                790,
                775,
                791,
                773,
                791,
                771,
                789,
                771,
                778,
                773,
                770
            ],
            "class": "vehicle"
        },
        {
            "polygon": [
                845,
                767,
                861,
                767,
                864,
                771,
                870,
                771,
                871,
                772,
                893,
                772,
                898,
                775,
                903,
                780,
                905,
                795,
                905,
                808,
                903,
                809,
                898,
                809,
                896,
                808,
                896,
                805,
                887,
                805,
                885,
                806,
                874,
                806,
                872,
                805,
                868,
                805,
                867,
                808,
                866,
                810,
                862,
                810,
                860,
                808,
                860,
                798,
                860,
                794,
                848,
                794,
                848,
                796,
                847,
                797,
                845,
                797,
                843,
                796,
                843,
                790,
                841,
                790,
                838,
                790,
                838,
                788,
                838,
                780,
                841,
                774,
                843,
                770
            ],
            "class": "vehicle"
        },
        {
            "polygon": [
                1723,
                703,
                1693,
                806,
                1695,
                811,
                1798,
                795,
                1799,
                787,
                1732,
                701
            ],
            "class": "trafficSign"
        },
        {
            "polygon": [
                601,
                817,
                600,
                807,
                602,
                807,
                605,
                817,
                616,
                835,
                615,
                805,
                620,
                804,
                624,
                839,
                605,
                839,
                600,
                837
            ],
            "class": "background"
        },
        {
            "polygon": [
                631,
                802,
                632,
                830,
                635,
                829,
                634,
                802
            ],
            "class": "background"
        },
        {
            "polygon": [
                642,
                802,
                643,
                828,
                646,
                828,
                645,
                802
            ],
            "class": "background"
        }
    ]
}